cli/__init__.py
cli/main.py
dataghost/__init__.py
dataghost-0.1.1.dist-info/licenses/LICENSE
ttd/__init__.py
ttd/dataghost.py
ttd/diff.py
ttd/logger.py
ttd/replay.py
ttd/storage.py
ttd/dashboard/__init__.py
ttd/dashboard/colab_utils.py
ttd/dashboard/server.py
ttd/dashboard/static/styles.css
ttd/dashboard/static/dist/dataghost_favicon.svg
ttd/dashboard/static/dist/index.html
ttd/dashboard/static/dist/assets/index-CuK3CaKs.css
ttd/dashboard/static/dist/assets/index-nCBJ-AkJ.js
ttd/dashboard/templates/dashboard.html
ttd/integrations/__init__.py
ttd/integrations/airflow.py
dataghost-0.1.1.dist-info/METADATA
dataghost-0.1.1.dist-info/WHEEL
dataghost-0.1.1.dist-info/entry_points.txt
dataghost-0.1.1.dist-info/top_level.txt
dataghost-0.1.1.dist-info/RECORD
