Metadata-Version: 2.4
Name: dataghost
Version: 0.1.1
Summary: Time-Travel Debugger for Data Pipelines
Home-page: https://github.com/dataghost/dataghost
Author: Krish Shah
Author-email: Krish Shah <2003kshah@gmail.com>
License: MIT
Project-URL: Homepage, https://github.com/dataghost/dataghost
Project-URL: Repository, https://github.com/dataghost/dataghost
Project-URL: Documentation, https://github.com/dataghost/dataghost/docs
Project-URL: Bug Tracker, https://github.com/dataghost/dataghost/issues
Keywords: debugging,data-pipelines,time-travel,airflow,data-engineering
Classifier: Development Status :: 3 - Alpha
Classifier: Intended Audience :: Developers
Classifier: License :: OSI Approved :: MIT License
Classifier: Programming Language :: Python :: 3
Classifier: Programming Language :: Python :: 3.8
Classifier: Programming Language :: Python :: 3.9
Classifier: Programming Language :: Python :: 3.10
Classifier: Programming Language :: Python :: 3.11
Classifier: Topic :: Software Development :: Debuggers
Classifier: Topic :: Software Development :: Libraries :: Python Modules
Requires-Python: >=3.8
License-File: LICENSE
Requires-Dist: cloudpickle>=2.0.0
Requires-Dist: duckdb>=0.8.0
Requires-Dist: lz4>=4.0.0
Requires-Dist: pandas>=1.5.0
Requires-Dist: psutil>=5.9.0
Requires-Dist: typer[all]>=0.9.0
Requires-Dist: rich>=13.0.0
Provides-Extra: deepdiff
Requires-Dist: deepdiff>=6.0.0; extra == "deepdiff"
Provides-Extra: airflow
Requires-Dist: apache-airflow>=2.5.0; extra == "airflow"
Provides-Extra: s3
Requires-Dist: boto3>=1.26.0; extra == "s3"
Requires-Dist: fsspec>=2023.1.0; extra == "s3"
Provides-Extra: dashboard
Requires-Dist: fastapi>=0.104.0; extra == "dashboard"
Requires-Dist: uvicorn[standard]>=0.24.0; extra == "dashboard"
Requires-Dist: jinja2>=3.1.0; extra == "dashboard"
Provides-Extra: tunnel
Requires-Dist: pyngrok>=5.0.0; extra == "tunnel"
Provides-Extra: colab
Requires-Dist: fastapi>=0.104.0; extra == "colab"
Requires-Dist: uvicorn[standard]>=0.24.0; extra == "colab"
Requires-Dist: jinja2>=3.1.0; extra == "colab"
Requires-Dist: pyngrok>=5.0.0; extra == "colab"
Provides-Extra: dev
Requires-Dist: pytest>=7.0.0; extra == "dev"
Requires-Dist: pytest-cov>=4.0.0; extra == "dev"
Requires-Dist: black>=23.0.0; extra == "dev"
Requires-Dist: isort>=5.12.0; extra == "dev"
Requires-Dist: flake8>=6.0.0; extra == "dev"
Requires-Dist: mypy>=1.0.0; extra == "dev"
Requires-Dist: pre-commit>=3.0.0; extra == "dev"
Provides-Extra: all
Requires-Dist: deepdiff>=6.0.0; extra == "all"
Requires-Dist: apache-airflow>=2.5.0; extra == "all"
Requires-Dist: boto3>=1.26.0; extra == "all"
Requires-Dist: fsspec>=2023.1.0; extra == "all"
Requires-Dist: fastapi>=0.104.0; extra == "all"
Requires-Dist: uvicorn[standard]>=0.24.0; extra == "all"
Requires-Dist: jinja2>=3.1.0; extra == "all"
Requires-Dist: pyngrok>=5.0.0; extra == "all"
Dynamic: author
Dynamic: home-page
Dynamic: license-file
Dynamic: requires-python
